p3do/__init__.py
p3do/cli.py
p3do/cli_utils.py
p3do/github.py
p3do/graphsearch.py
p3do/jenkins.py
p3do/keycloak.py
p3do/poolparty.py
p3do-0.9.4.dist-info/LICENSE
p3do-0.9.4.dist-info/METADATA
p3do-0.9.4.dist-info/WHEEL
p3do-0.9.4.dist-info/entry_points.txt
p3do-0.9.4.dist-info/RECORD
