Metadata-Version: 2.1
Name: p3do
Version: 0.9.4
Summary: CLI utilities for p3d
License: MIT
Author: Armin Friedl
Author-email: armin.friedl@semantic-web.com
Requires-Python: >=3.8,<4.0
Classifier: License :: OSI Approved :: MIT License
Classifier: Programming Language :: Python :: 3
Classifier: Programming Language :: Python :: 3.8
Classifier: Programming Language :: Python :: 3.9
Classifier: Programming Language :: Python :: 3.10
Classifier: Programming Language :: Python :: 3.11
Requires-Dist: Flask (>=3.0.2,<4.0.0)
Requires-Dist: appdirs (>=1.4.4,<2.0.0)
Requires-Dist: click (>=8.1,<9.0)
Requires-Dist: cryptography (>=42.0.0,<43.0.0)
Requires-Dist: jenkinsapi (>=0.3.11,<0.4.0)
Requires-Dist: loguru (>=0.7.2,<0.8.0)
Requires-Dist: pygithub (>=2.2.0,<3.0.0)
Requires-Dist: python-keycloak (>=3.9.0,<4.0.0)
Requires-Dist: python-lorem (>=1.3.0.post1,<2.0.0)
Requires-Dist: rich (>=13.7.0,<14.0.0)
